src/woodder.py
woodder-1.0.0.dist-info/LICENSE
woodder-1.0.0.dist-info/METADATA
woodder-1.0.0.dist-info/WHEEL
woodder-1.0.0.dist-info/top_level.txt
woodder-1.0.0.dist-info/RECORD
