Metadata-Version: 2.1
Name: woodder
Version: 1.0.0
Summary: A really simple logger configurator for Python 3.
Home-page: https://github.com/ArshanKhanifar/woodder
Author: Arshan Khanifar
Author-email: arshankhanifar@gmail.com
License: MIT
Platform: UNKNOWN
Classifier: License :: OSI Approved :: MIT License
Classifier: Programming Language :: Python :: 3
Classifier: Programming Language :: Python :: 3.9
